setup.cfg
setup.py
easymlpy/__init__.py
easymlpy/core.py
easymlpy/datasets.py
easymlpy/glmnet.py
easymlpy/measure.py
easymlpy/plot.py
easymlpy/preprocess.py
easymlpy/random_forest.py
easymlpy/resample.py
easymlpy/setters.py
easymlpy/support_vector_machine.py
easymlpy/utils.py
easymlpy.egg-info/PKG-INFO
easymlpy.egg-info/SOURCES.txt
easymlpy.egg-info/dependency_links.txt
easymlpy.egg-info/top_level.txt