Metadata-Version: 1.0
Name: easymlpy
Version: 0.1.1
Summary: A Python toolkit for easily building and evaluating machine learning models.
Home-page: https://github.com/CCS-Lab/easyml
Author: OSU CCSL
Author-email: paul.hendricks.2013@owu.edu
License: MIT
Keywords: easy machine learning glmnet penalized regression random forest penalized regression
Platform: UNKNOWN
